README.md
setup.cfg
setup.py
customjson/__init__.py
customjson/cli.py
customjson/custom.py
customjson/defaults.py
customjson/version.py
customjson.egg-info/PKG-INFO
customjson.egg-info/SOURCES.txt
customjson.egg-info/dependency_links.txt
customjson.egg-info/entry_points.txt
customjson.egg-info/requires.txt
customjson.egg-info/top_level.txt
customjson/cards/__init__.py
customjson/cards/ciotlosm.py
customjson/cards/isabellaalstrom.py
customjson/cards/maykar.py
customjson/cards/org.py
customjson/cards/thomasloven.py
customjson/components/__init__.py
customjson/components/custom_updater.py
customjson/components/isabellaalstrom.py
customjson/components/org.py