Metadata-Version: 2.1
Name: customjson
Version: 2.11.1
Summary: UNKNOWN
Home-page: https://github.com/ludeeus/customjson
Author: Joakim Sorensen
Author-email: ludeeus@gmail.com
License: UNKNOWN
Platform: UNKNOWN
Classifier: Programming Language :: Python :: 3
Classifier: License :: OSI Approved :: MIT License
Classifier: Operating System :: OS Independent
